p3man/__init__.py
p3man/account.py
p3man/constant.py
p3man/db.py
p3man/encryption.py
p3man/messages.py
p3man/queries.py
p3man-0.1.2.dist-info/entry_points.txt
p3man-0.1.2.dist-info/WHEEL
p3man-0.1.2.dist-info/METADATA
p3man-0.1.2.dist-info/RECORD
